django_magnificent_messages/__init__.py
django_magnificent_messages/apps.py
django_magnificent_messages/backend.py
django_magnificent_messages/conf.py
django_magnificent_messages/constants.py
django_magnificent_messages/context_processors.py
django_magnificent_messages/fields.py
django_magnificent_messages/messages.py
django_magnificent_messages/middleware.py
django_magnificent_messages/models.py
django_magnificent_messages/notifications.py
django_magnificent_messages/system_messages.py
django_magnificent_messages/urls.py
django_magnificent_messages/views.py
django_magnificent_messages/migrations/0001_initial.py
django_magnificent_messages/migrations/0002_auto_20191201_1245.py
django_magnificent_messages/migrations/0003_auto_20200118_2058.py
django_magnificent_messages/migrations/__init__.py
django_magnificent_messages/static/css/django_magnificent_messages.css
django_magnificent_messages/static/js/django_magnificent_messages.js
django_magnificent_messages/storage/__init__.py
django_magnificent_messages/storage/base.py
django_magnificent_messages/storage/message_storage/__init__.py
django_magnificent_messages/storage/message_storage/base.py
django_magnificent_messages/storage/message_storage/db.py
django_magnificent_messages/storage/message_storage/db_signals.py
django_magnificent_messages/storage/notification_storage/__init__.py
django_magnificent_messages/storage/notification_storage/base.py
django_magnificent_messages/storage/notification_storage/cookie.py
django_magnificent_messages/storage/notification_storage/fallback.py
django_magnificent_messages/storage/notification_storage/session.py
django_magnificent_messages/templatetags/__init__.py
django_magnificent_messages/templatetags/dmm_templatetags.py
django_magnificent_messages-0.3.1.dist-info/AUTHORS
django_magnificent_messages-0.3.1.dist-info/AUTHORS.rst
django_magnificent_messages-0.3.1.dist-info/LICENSE
django_magnificent_messages-0.3.1.dist-info/METADATA
django_magnificent_messages-0.3.1.dist-info/WHEEL
django_magnificent_messages-0.3.1.dist-info/pbr.json
django_magnificent_messages-0.3.1.dist-info/top_level.txt
django_magnificent_messages-0.3.1.dist-info/RECORD
